<annotation>
  <folder>team36</folder>
  <filename>team36_038.jpg</filename>
  <source>
    <database>Unknown</database>
    <annotation>Unknown</annotation>
    <image>Unknown</image>
  </source>
  <size>
    <width>3024</width>
    <height>4032</height>
    <depth />
  </size>
  <segmented>0</segmented>
  <object>
    <name>duck_specialty</name>
    <pose>Unspecified</pose><truncated>0</truncated>
    <occluded>0</occluded>
    <difficult>0</difficult>
    <bndbox>
      <xmin>1017</xmin>
      <ymin>1349</ymin>
      <xmax>2002</xmax>
      <ymax>2277</ymax>
    </bndbox>
    <attributes>
      <attribute>
        <name>rotation</name>
        <value>0.0</value>
      </attribute>
    </attributes>
  </object>
</annotation>