<annotation>
	<folder></folder>
	<filename>team12_175.jpg</filename>
	<path>team12_175.jpg</path>
	<source>
		<database>roboflow.com</database>
	</source>
	<size>
		<width>640</width>
		<height>640</height>
		<depth>3</depth>
	</size>
	<segmented>0</segmented>
	<object>
		<name>sign_yield</name>
		<pose>Unspecified</pose>
		<truncated>0</truncated>
		<difficult>0</difficult>
		<occluded>0</occluded>
		<bndbox>
			<xmin>422</xmin>
			<xmax>542</xmax>
			<ymin>174</ymin>
			<ymax>392</ymax>
		</bndbox>
		<polygon>
			<x1>465.553663</x1>
			<y1>387.636364</y1>
			<x2>481.908007</x2>
			<y2>391.272727</y2>
			<x3>487.359455</x3>
			<y3>384.727273</y3>
			<x4>492.265758</x4>
			<y4>372.363636</y4>
			<x5>514.07155</x5>
			<y5>301.818182</y5>
			<x6>535.877342</x6>
			<y6>219.636364</y6>
			<x7>541.32879</x7>
			<y7>192</y7>
			<x8>540.783646</x8>
			<y8>177.454545</y8>
			<x9>534.787053</x9>
			<y9>173.090909</y9>
			<x10>528.245315</x10>
			<y10>173.818182</y10>
			<x11>448.109029</x11>
			<y11>198.545455</y11>
			<x12>438.296422</x12>
			<y12>203.636364</y12>
			<x13>425.758092</x13>
			<y13>215.272727</y13>
			<x14>421.396934</x14>
			<y14>224</y14>
			<x15>423.032368</x15>
			<y15>248.727273</y15>
			<x16>445.383305</x16>
			<y16>319.272727</y16>
			<x17>459.55707</x17>
			<y17>375.272727</y17>
			<x18>465.553663</x18>
			<y18>387.636364</y18>
		</polygon>
	</object>
</annotation>
