<annotation>
	<folder></folder>
	<filename>team12_144.jpg</filename>
	<path>team12_144.jpg</path>
	<source>
		<database>roboflow.com</database>
	</source>
	<size>
		<width>640</width>
		<height>640</height>
		<depth>3</depth>
	</size>
	<segmented>0</segmented>
	<object>
		<name>duck_regular</name>
		<pose>Unspecified</pose>
		<truncated>0</truncated>
		<difficult>0</difficult>
		<occluded>0</occluded>
		<bndbox>
			<xmin>70</xmin>
			<xmax>169</xmax>
			<ymin>488</ymin>
			<ymax>601</ymax>
		</bndbox>
		<polygon>
			<x1>72.504259</x1>
			<y1>581.090909</y1>
			<x2>86.678024</x2>
			<y2>592</y2>
			<x3>105.212947</x3>
			<y3>599.272727</y3>
			<x4>117.751278</x4>
			<y4>600</y4>
			<x5>141.737649</x5>
			<y5>594.181818</y5>
			<x6>157.546848</x6>
			<y6>578.181818</y6>
			<x7>164.088586</x7>
			<y7>561.454545</y7>
			<x8>168.449744</x8>
			<y8>521.454545</y8>
			<x9>166.269165</x9>
			<y9>512.727273</y9>
			<x10>160.272572</x10>
			<y10>504</y10>
			<x11>154.27598</x11>
			<y11>501.090909</y11>
			<x12>145.008518</x12>
			<y12>503.272727</y12>
			<x13>136.286201</x13>
			<y13>490.909091</y13>
			<x14>130.289608</x14>
			<y14>487.272727</y14>
			<x15>122.112436</x15>
			<y15>486.545455</y15>
			<x16>114.480409</x16>
			<y16>489.454545</y16>
			<x17>106.303237</x17>
			<y17>496.727273</y17>
			<x18>91.584327</x18>
			<y18>502.545455</y18>
			<x19>81.771721</x19>
			<y19>516.363636</y19>
			<x20>76.320273</x20>
			<y20>531.636364</y20>
			<x21>73.594549</x21>
			<y21>554.181818</y21>
			<x22>69.23339</x22>
			<y22>565.090909</y22>
			<x23>69.23339</x23>
			<y23>573.090909</y23>
			<x24>72.504259</x24>
			<y24>581.090909</y24>
		</polygon>
	</object>
	<object>
		<name>sign_oneway_left</name>
		<pose>Unspecified</pose>
		<truncated>0</truncated>
		<difficult>0</difficult>
		<occluded>0</occluded>
		<bndbox>
			<xmin>432</xmin>
			<xmax>533</xmax>
			<ymin>292</ymin>
			<ymax>394</ymax>
		</bndbox>
		<polygon>
			<x1>532.197615</x1>
			<y1>290.909091</y1>
			<x2>442.930153</x2>
			<y2>320</y2>
			<x3>431.345826</x3>
			<y3>392.727273</y3>
			<x4>517.887564</x4>
			<y4>356.363636</y4>
			<x5>532.197615</x5>
			<y5>290.909091</y5>
		</polygon>
	</object>
	<object>
		<name>sign_oneway_right</name>
		<pose>Unspecified</pose>
		<truncated>0</truncated>
		<difficult>0</difficult>
		<occluded>0</occluded>
		<bndbox>
			<xmin>287</xmin>
			<xmax>373</xmax>
			<ymin>117</ymin>
			<ymax>180</ymax>
		</bndbox>
		<polygon>
			<x1>372.061329</x1>
			<y1>139.090909</y1>
			<x2>289.608177</x2>
			<y2>116.363636</y2>
			<x3>286.201022</x3>
			<y3>151.818182</y3>
			<x4>365.92845</x4>
			<y4>179.090909</y4>
			<x5>372.061329</x5>
			<y5>139.090909</y5>
		</polygon>
	</object>
	<object>
		<name>duck_specialty</name>
		<pose>Unspecified</pose>
		<truncated>0</truncated>
		<difficult>0</difficult>
		<occluded>0</occluded>
		<bndbox>
			<xmin>84</xmin>
			<xmax>132</xmax>
			<ymin>97</ymin>
			<ymax>163</ymax>
		</bndbox>
		<polygon>
			<x1>109.028961</x1>
			<y1>162.424</y1>
			<x2>123.929404</x2>
			<y2>161.939636</y2>
			<x3>130.834753</x3>
			<y3>151.757818</y3>
			<x4>130.471141</x4>
			<y4>137.212364</y4>
			<x5>122.476048</x5>
			<y5>131.394182</y5>
			<x6>124.293015</x6>
			<y6>120.727273</y6>
			<x7>122.112436</x7>
			<y7>109.576</y7>
			<x8>114.84402</x8>
			<y8>96.485091</y8>
			<x9>105.39448</x9>
			<y9>96</y9>
			<x10>97.399387</x10>
			<y10>100.363636</y10>
			<x11>94.491584</x11>
			<y11>113.939636</y11>
			<x12>83.588688</x12>
			<y12>132.363636</y12>
			<x13>82.86201</x13>
			<y13>157.090909</y13>
			<x14>109.028961</x14>
			<y14>162.424</y14>
		</polygon>
	</object>
	<object>
		<name>road_crosswalk</name>
		<pose>Unspecified</pose>
		<truncated>0</truncated>
		<difficult>0</difficult>
		<occluded>0</occluded>
		<bndbox>
			<xmin>98</xmin>
			<xmax>257</xmax>
			<ymin>160</ymin>
			<ymax>206</ymax>
		</bndbox>
		<polygon>
			<x1>256.218058</x1>
			<y1>204.605818</y1>
			<x2>250.039932</x2>
			<y2>176.485091</y2>
			<x3>126.109983</x3>
			<y3>158.545455</y3>
			<x4>106.848382</x4>
			<y4>160.485091</y4>
			<x5>96.672164</x5>
			<y5>180.848727</y5>
			<x6>256.218058</x6>
			<y6>204.605818</y6>
		</polygon>
	</object>
	<object>
		<name>road_oneway</name>
		<pose>Unspecified</pose>
		<truncated>0</truncated>
		<difficult>0</difficult>
		<occluded>0</occluded>
		<bndbox>
			<xmin>349</xmin>
			<xmax>396</xmax>
			<ymin>287</ymin>
			<ymax>308</ymax>
		</bndbox>
	</object>
	<object>
		<name>road_oneway</name>
		<pose>Unspecified</pose>
		<truncated>0</truncated>
		<difficult>0</difficult>
		<occluded>0</occluded>
		<bndbox>
			<xmin>435</xmin>
			<xmax>474</xmax>
			<ymin>287</ymin>
			<ymax>309</ymax>
		</bndbox>
	</object>
	<object>
		<name>road_oneway</name>
		<pose>Unspecified</pose>
		<truncated>0</truncated>
		<difficult>0</difficult>
		<occluded>0</occluded>
		<bndbox>
			<xmin>527</xmin>
			<xmax>556</xmax>
			<ymin>304</ymin>
			<ymax>323</ymax>
		</bndbox>
	</object>
</annotation>
