<annotation>
	<folder></folder>
	<filename>team12_071.jpg</filename>
	<path>team12_071.jpg</path>
	<source>
		<database>roboflow.com</database>
	</source>
	<size>
		<width>640</width>
		<height>640</height>
		<depth>3</depth>
	</size>
	<segmented>0</segmented>
	<object>
		<name>sign_oneway_left</name>
		<pose>Unspecified</pose>
		<truncated>0</truncated>
		<difficult>0</difficult>
		<occluded>0</occluded>
		<bndbox>
			<xmin>110</xmin>
			<xmax>210</xmax>
			<ymin>287</ymin>
			<ymax>339</ymax>
		</bndbox>
		<polygon>
			<x1>204.673526</x1>
			<y1>286.170909</y1>
			<x2>108.72586</x2>
			<y2>300.808</y2>
			<x3>115.343918</x3>
			<y3>337.874182</y3>
			<x4>209.215673</x4>
			<y4>327.371636</y4>
			<x5>204.673526</x5>
			<y5>286.170909</y5>
		</polygon>
	</object>
	<object>
		<name>sign_stop</name>
		<pose>Unspecified</pose>
		<truncated>0</truncated>
		<difficult>0</difficult>
		<occluded>0</occluded>
		<bndbox>
			<xmin>412</xmin>
			<xmax>480</xmax>
			<ymin>283</ymin>
			<ymax>363</ymax>
		</bndbox>
		<polygon>
			<x1>429.663509</x1>
			<y1>361.705455</y1>
			<x2>456.008177</x2>
			<y2>361.301818</y2>
			<x3>477.810698</x3>
			<y3>337.066182</y3>
			<x4>479.325111</x4>
			<y4>306.770909</y4>
			<x5>459.339012</x5>
			<y5>282.131636</y5>
			<x6>432.086133</x6>
			<y6>286.170909</y6>
			<x7>412.403135</x7>
			<y7>307.578909</y7>
			<x8>411.191823</x8>
			<y8>343.528727</y8>
			<x9>429.663509</x9>
			<y9>361.705455</y9>
		</polygon>
	</object>
</annotation>
